{
  "created_at": "2026-03-26T21:18:35.943298+00:00",
  "signatures": {
    "85e0ceeb6d92f5a5": {
      "hash": "85e0ceeb6d92f5a5",
      "service": "api-gateway",
      "error_type": "503",
      "http_status": "",
      "db_system": "",
      "operation": "GET vets-service",
      "call_path": "",
      "occurrences": 20,
      "watch_hits": 1,
      "auto_promoted": false,
      "promoted_at": null,
      "first_seen": "2026-03-27T03:40:29.087207+00:00"
    },
    "81fb554dfa05696c": {
      "hash": "81fb554dfa05696c",
      "service": "vets-service",
      "error_type": "java.net.ConnectException",
      "http_status": "",
      "db_system": "",
      "operation": "GET",
      "call_path": "",
      "occurrences": 4,
      "watch_hits": 1,
      "auto_promoted": false,
      "promoted_at": null,
      "first_seen": "2026-03-27T03:40:29.306395+00:00"
    }
  },
  "learn_runs": 3,
  "updated_at": "2026-03-27T04:01:05.710279+00:00",
  "environment": "petclinicmbtest"
}